requirements.txt
setup.py
pypi_slug/__init__.py
pypi_slug.egg-info/PKG-INFO
pypi_slug.egg-info/SOURCES.txt
pypi_slug.egg-info/dependency_links.txt
pypi_slug.egg-info/top_level.txt