Metadata-Version: 2.1
Name: pypi-slug
Version: 2020.7.2
Summary: pypi project slug
Home-page: https://github.com/andrewp-as-is/pypi-slug.py
License: Unlicense
Keywords: pypi
Platform: UNKNOWN
Classifier: License :: Public Domain
Classifier: Operating System :: OS Independent
Classifier: Programming Language :: Python :: 3
